conftool/__init__.py
conftool/action.py
conftool/audit.py
conftool/backend.py
conftool/configuration.py
conftool/kvobject.py
conftool/loader.py
conftool/node.py
conftool/types.py
conftool/cli/__init__.py
conftool/cli/conftool2git.py
conftool/cli/syncer.py
conftool/cli/tool.py
conftool/drivers/__init__.py
conftool/drivers/etcd.py
conftool/extensions/__init__.py
conftool/extensions/dbconfig/__init__.py
conftool/extensions/dbconfig/action.py
conftool/extensions/dbconfig/cli.py
conftool/extensions/dbconfig/config.py
conftool/extensions/dbconfig/entities.py
conftool/tests/__init__.py
conftool/tests/integration/__init__.py
conftool/tests/integration/test_all.py
conftool/tests/integration/test_ct2git.py
conftool/tests/integration/test_dbconfig.py
conftool/tests/integration/test_driver_etcd.py
conftool/tests/integration/test_syncer.py
conftool/tests/integration/test_tool.py
conftool/tests/unit/__init__.py
conftool/tests/unit/test_action.py
conftool/tests/unit/test_audit.py
conftool/tests/unit/test_backend.py
conftool/tests/unit/test_cli_tool.py
conftool/tests/unit/test_ct2git.py
conftool/tests/unit/test_dbconfig.py
conftool/tests/unit/test_driver_etcd.py
conftool/tests/unit/test_kvobject.py
conftool/tests/unit/test_loader.py
conftool/tests/unit/test_node.py
conftool/tests/unit/test_syncer.py
conftool/tests/unit/test_types.py
conftool-6.1.0.dist-info/licenses/LICENSE
conftool-6.1.0.dist-info/METADATA
conftool-6.1.0.dist-info/WHEEL
conftool-6.1.0.dist-info/entry_points.txt
conftool-6.1.0.dist-info/top_level.txt
conftool-6.1.0.dist-info/RECORD
