Metadata-Version: 2.4
Name: conftool
Version: 6.1.0
Summary: Tools to interoperate with distributed k/v stores
Home-page: https://github.com/wikimedia/operations-software-conftool
Author: Joe
Author-email: joe@wikimedia.org
Classifier: Development Status :: 5 - Production/Stable
Classifier: Intended Audience :: System Administrators
Classifier: License :: OSI Approved :: GNU General Public License v3 or later (GPLv3+)
Classifier: Operating System :: POSIX :: Linux
Classifier: Programming Language :: Python :: 3
Classifier: Topic :: System :: Clustering
License-File: LICENSE
Requires-Dist: python-etcd>=0.4.3
Requires-Dist: pyyaml
Requires-Dist: jsonschema
Provides-Extra: with-dbctl
Provides-Extra: with-conftool2git
Requires-Dist: pygit2; extra == "with-conftool2git"
Requires-Dist: aiohttp; extra == "with-conftool2git"
Dynamic: author
Dynamic: author-email
Dynamic: classifier
Dynamic: home-page
Dynamic: license-file
Dynamic: provides-extra
Dynamic: requires-dist
Dynamic: summary
